{
  "name": "calculator",
  "productName": "calculator",
  "version": "1.0.0",
  "description": "A Simple calculator Project using electron js.",
  "main": "src/index.js",
  "scripts": {
    "start": "electron-forge start",
    "package": "electron-forge package",
    "make": "electron-forge make",
    "publish": "electron-forge publish",
    "lint": "echo \"No linting configured\""
  },
  "keywords": [],
  "author": {
    "name": "iamevs",
    "email": "iamevs143@gmail.com"
  },
  "license": "MIT",
  "config": {
    "forge": {
      "packagerConfig": {},
      "makers": [
        {
          "name": "@electron-forge/maker-squirrel",
          "config": {
            "name": "calculator"
          }
        },
        {
          "name": "@electron-forge/maker-zip",
          "platforms": [
            "darwin"
          ]
        },
        {
          "name": "@electron-forge/maker-deb",
          "config": {}
        },
        {
          "name": "@electron-forge/maker-rpm",
          "config": {}
        }
      ]
    }
  },
  "dependencies": {
    "concurrently": "^7.4.0",
    "cross-env": "^7.0.3",
    "electron-squirrel-startup": "^1.0.0",
    "react": "^18.2.0",
    "wait-on": "^6.0.1"
  },
  "devDependencies": {
    "@electron-forge/cli": "^6.0.0-beta.65",
    "@electron-forge/maker-deb": "^6.0.0-beta.65",
    "@electron-forge/maker-rpm": "^6.0.0-beta.65",
    "@electron-forge/maker-squirrel": "^6.0.0-beta.65",
    "@electron-forge/maker-zip": "^6.0.0-beta.65",
    "electron": "^21.1.1"
  }
}
